fileextractor/__init__.py
fileextractor/extractor.py
fileextractor-0.1.1.dist-info/METADATA
fileextractor-0.1.1.dist-info/WHEEL
fileextractor-0.1.1.dist-info/top_level.txt
fileextractor-0.1.1.dist-info/RECORD
